lifeblood/__init__.py
lifeblood/aiosqlite_overlay.py
lifeblood/attribute_serialization.py
lifeblood/base.py
lifeblood/basenode.py
lifeblood/basenode_serialization.py
lifeblood/basenode_serializer_v1.py
lifeblood/basenode_serializer_v2.py
lifeblood/broadcasting.py
lifeblood/buffer_serializable.py
lifeblood/buffered_connection.py
lifeblood/common_serialization.py
lifeblood/component_base.py
lifeblood/component_process_wrapper.py
lifeblood/config.py
lifeblood/db_misc.py
lifeblood/defaults.py
lifeblood/enums.py
lifeblood/environment_resolver.py
lifeblood/exceptions.py
lifeblood/expiring_collections.py
lifeblood/expression_locals_provider_base.py
lifeblood/filelock.py
lifeblood/hardware_resources.py
lifeblood/invocationjob.py
lifeblood/launch.py
lifeblood/local_notifier.py
lifeblood/logging.py
lifeblood/main_scheduler.py
lifeblood/main_worker.py
lifeblood/main_workerpool.py
lifeblood/maintenance.py
lifeblood/matrix_helper.py
lifeblood/message_processor_ping_generic_handler.py
lifeblood/misc.py
lifeblood/names.py
lifeblood/nethelpers.py
lifeblood/node_dataprovider_base.py
lifeblood/node_parameters.py
lifeblood/node_plugin_base.py
lifeblood/node_type_metadata.py
lifeblood/node_ui.py
lifeblood/node_ui_callback_receiver_base.py
lifeblood/node_visualization_classes.py
lifeblood/nodegraph_holder_base.py
lifeblood/nodethings.py
lifeblood/os_based_cheats.py
lifeblood/paths.py
lifeblood/plugin_info.py
lifeblood/pluginloader.py
lifeblood/process_utils.py
lifeblood/processingcontext.py
lifeblood/pulse_checker.py
lifeblood/rwlock.py
lifeblood/scheduler_config_provider_base.py
lifeblood/scheduler_config_provider_default.py
lifeblood/scheduler_config_provider_file.py
lifeblood/scheduler_event_log.py
lifeblood/scheduler_message_processor.py
lifeblood/scheduler_message_processor_client.py
lifeblood/scheduler_task_protocol.py
lifeblood/scheduler_ui_protocol.py
lifeblood/shared_lazy_sqlite_connection.py
lifeblood/simple_worker_pool.py
lifeblood/simple_worker_pool_main.py
lifeblood-0.13.0.dist-info/METADATA
lifeblood-0.13.0.dist-info/WHEEL
lifeblood-0.13.0.dist-info/entry_points.txt
lifeblood-0.13.0.dist-info/top_level.txt
lifeblood-0.13.0.dist-info/RECORD
