Metadata-Version: 2.4
Name: lifeblood
Version: 0.13.0
Summary: LIFEBLOOD !!
Home-page: https://github.com/pedohorse/lifeblood
Author: XAPKOHHEH
Project-URL: Bug Tracker, https://github.com/pedohorse/lifeblood/issues
Classifier: Programming Language :: Python :: 3
Classifier: License :: OSI Approved :: GNU General Public License v3 or later (GPLv3+)
Classifier: Operating System :: OS Independent
Requires-Python: <3.12,>=3.8
Requires-Dist: aiofiles~=0.8
Requires-Dist: aiosqlite~=0.17
Requires-Dist: aiorwlock~=1.3
Requires-Dist: lz4~=4.0
Requires-Dist: psutil~=5.8
Requires-Dist: pywin32==306; platform_system == "Windows"
Requires-Dist: semantic-version~=2.10
Requires-Dist: toml~=0.10
Requires-Dist: watchdog~=2.1
